{
  "updated": "14-07-2026 01:19 PM Colombia",
  "version": "V4.5",
  "status": {
    "updated": "14-07-2026 01:19 PM Colombia",
    "version": "V4.5",
    "engine": "PAPER_TRADING_ENGINE",
    "mode": "PAPER_ONLY_NO_REAL_ORDERS",
    "health": "WARNING",
    "warnings_count": 1,
    "warnings": [
      "Diagnóstico general marca riesgo ALTO."
    ],
    "market": {
      "estado": "ALCISTA",
      "score": 8,
      "spy20": 1.73,
      "qqq20": 0.16,
      "drivers": {
        "ARKK": {
          "ticker": "ARKK",
          "estado": "POSITIVO",
          "score": 3,
          "mom20": 5.32,
          "mom5": -1.87
        },
        "BTC-USD": {
          "ticker": "BTC-USD",
          "estado": "POSITIVO",
          "score": 3,
          "mom20": 5.71,
          "mom5": 2.04
        },
        "CL=F": {
          "ticker": "CL=F",
          "estado": "NEUTRO",
          "score": 0,
          "mom20": -6.86,
          "mom5": 12.24
        },
        "ETH-USD": {
          "ticker": "ETH-USD",
          "estado": "POSITIVO",
          "score": 3,
          "mom20": 15.41,
          "mom5": 7.17
        },
        "QQQ": {
          "ticker": "QQQ",
          "estado": "POSITIVO",
          "score": 3,
          "mom20": 0.16,
          "mom5": 1.73
        },
        "SOXX": {
          "ticker": "SOXX",
          "estado": "NEUTRO",
          "score": 0,
          "mom20": -3.92,
          "mom5": 3.8
        },
        "SPY": {
          "ticker": "SPY",
          "estado": "FUERTE",
          "score": 6,
          "mom20": 1.73,
          "mom5": 0.66
        },
        "XLE": {
          "ticker": "XLE",
          "estado": "NEUTRO",
          "score": 0,
          "mom20": -0.76,
          "mom5": 3.78
        }
      },
      "sectores": {
        "chips": {
          "estado": "NEUTRO +",
          "score": 3,
          "mom20_prom": -1.88,
          "detalle": "SOXX -3.92% · QQQ 0.16%",
          "drivers": [
            "SOXX",
            "QQQ"
          ]
        },
        "energia": {
          "estado": "NEUTRO",
          "score": 0,
          "mom20_prom": -3.81,
          "detalle": "XLE -0.76% · CL=F -6.86%",
          "drivers": [
            "XLE",
            "CL=F"
          ]
        },
        "cripto": {
          "estado": "NEUTRO +",
          "score": 3,
          "mom20_prom": 10.56,
          "detalle": "BTC-USD 5.71% · ETH-USD 15.41%",
          "drivers": [
            "BTC-USD",
            "ETH-USD"
          ]
        },
        "tech_ia": {
          "estado": "ACOMPAÑA",
          "score": 7,
          "mom20_prom": 2.4,
          "detalle": "QQQ 0.16% · ARKK 5.32% · SPY 1.73%",
          "drivers": [
            "QQQ",
            "ARKK",
            "SPY"
          ]
        }
      }
    },
    "positions_open": 5,
    "orders_total": 595,
    "trades_closed": 295,
    "signals_available": 275,
    "broker_real_enabled": false,
    "operational_mode": "NORMAL",
    "files": {
      "portfolio": "paper/paper_portfolio.json",
      "orders": "paper/paper_orders.json",
      "trades": "paper/paper_trades.json",
      "risk": "paper/paper_risk.json",
      "status": "paper/paper_status.json",
      "state": "paper/paper_state.json",
      "audit": "paper/paper_audit.json",
      "operational_rules": "paper/paper_operational_rules.json"
    }
  },
  "portfolio": {
    "updated": "14-07-2026 01:19 PM Colombia",
    "version": "V4.5",
    "mode": "PAPER_TRADING_SIMULATED",
    "capital_initial_usd": 5000.0,
    "cash_model_note": "Cash derivado de simulación histórica; no representa cuenta broker real.",
    "closed_pnl_usd_estimated": 564.56,
    "open_pnl_usd_estimated": 23.7,
    "total_pnl_usd_estimated": 588.26,
    "exposure_usd": 3764.88,
    "exposure_pct": 75.3,
    "open_risk_usd": 67.92,
    "open_risk_pct": 1.36,
    "cash_equity_usd": 5564.56,
    "cash_committed_usd": 3741.18,
    "cash_available_usd": 1823.38,
    "cash_available_pct": 36.47,
    "max_nueva_posicion_usd": 1000.0,
    "open_positions": 5,
    "closed_trades": 295,
    "positions": [
      {
        "position_id": "2026-07-14-UBER",
        "ticker": "UBER",
        "sector": "Tecnología",
        "status": "OPEN",
        "entry_date": "2026-07-14",
        "days_open": 0,
        "entry_signal": "BUY",
        "current_signal": "BUY",
        "entry_price": 73.18,
        "current_price": 71.96,
        "quantity_estimated": 13.6649,
        "invested_usd": 1112.92,
        "market_value_usd": 1091.77,
        "open_pnl_usd": -21.15,
        "open_pnl_pct": -1.67,
        "stop": 71.76,
        "target": 75.6,
        "risk_usd": 21.6,
        "max_loss_stop_usd": 21.6,
        "risk_pct_account": 0.39,
        "distance_stop_pct": 0.28,
        "distance_target_pct": 5.06,
        "score_entry": 77.9,
        "score_current": 70.0,
        "market_entry": "NEUTRO +",
        "market_current": "ALCISTA",
        "result": "EN SEGUIMIENTO"
      },
      {
        "position_id": "2026-07-14-PLTR",
        "ticker": "PLTR",
        "sector": "IA / Software",
        "status": "OPEN",
        "entry_date": "2026-07-14",
        "days_open": 0,
        "entry_signal": "BUY",
        "current_signal": "BUY",
        "entry_price": 130.36,
        "current_price": 135.31,
        "quantity_estimated": 7.6711,
        "invested_usd": 890.33,
        "market_value_usd": 922.11,
        "open_pnl_usd": 31.78,
        "open_pnl_pct": 3.8,
        "stop": 126.85,
        "target": 136.33,
        "risk_usd": 23.97,
        "max_loss_stop_usd": 23.97,
        "risk_pct_account": 0.54,
        "distance_stop_pct": 6.25,
        "distance_target_pct": 0.75,
        "score_entry": 70.8,
        "score_current": 79.5,
        "market_entry": "NEUTRO +",
        "market_current": "ALCISTA",
        "result": "EN SEGUIMIENTO"
      },
      {
        "position_id": "2026-07-14-BX",
        "ticker": "BX",
        "sector": "Finanzas",
        "status": "OPEN",
        "entry_date": "2026-07-14",
        "days_open": 0,
        "entry_signal": "BUY",
        "current_signal": "BUY",
        "entry_price": 122.04,
        "current_price": 125.09,
        "quantity_estimated": 8.194,
        "invested_usd": 712.27,
        "market_value_usd": 728.44,
        "open_pnl_usd": 16.17,
        "open_pnl_pct": 2.5,
        "stop": 120.02,
        "target": 125.47,
        "risk_usd": 11.79,
        "max_loss_stop_usd": 11.79,
        "risk_pct_account": 0.33,
        "distance_stop_pct": 4.05,
        "distance_target_pct": 0.3,
        "score_entry": 74.1,
        "score_current": 80.0,
        "market_entry": "NEUTRO +",
        "market_current": "ALCISTA",
        "result": "EN SEGUIMIENTO"
      },
      {
        "position_id": "2026-07-13-XBI",
        "ticker": "XBI",
        "sector": "ETF Biotech",
        "status": "OPEN",
        "entry_date": "2026-07-13",
        "days_open": 1,
        "entry_signal": "BUY",
        "current_signal": "BUY",
        "entry_price": 156.15,
        "current_price": 156.01,
        "quantity_estimated": 6.4041,
        "invested_usd": 569.81,
        "market_value_usd": 567.99,
        "open_pnl_usd": -1.82,
        "open_pnl_pct": -0.09,
        "stop": 153.95,
        "target": 159.87,
        "risk_usd": 8.03,
        "max_loss_stop_usd": 8.03,
        "risk_pct_account": 0.28,
        "distance_stop_pct": 1.32,
        "distance_target_pct": 2.47,
        "score_entry": 68.0,
        "score_current": 77.2,
        "market_entry": "NEUTRO",
        "market_current": "ALCISTA",
        "result": "EN SEGUIMIENTO"
      },
      {
        "position_id": "2026-07-13-VTI",
        "ticker": "VTI",
        "sector": "ETF Mercado",
        "status": "OPEN",
        "entry_date": "2026-07-13",
        "days_open": 1,
        "entry_signal": "BUY",
        "current_signal": "BUY",
        "entry_price": 371.69,
        "current_price": 371.49,
        "quantity_estimated": 2.6904,
        "invested_usd": 455.85,
        "market_value_usd": 454.57,
        "open_pnl_usd": -1.28,
        "open_pnl_pct": -0.05,
        "stop": 369.63,
        "target": 375.19,
        "risk_usd": 2.53,
        "max_loss_stop_usd": 2.53,
        "risk_pct_account": 0.11,
        "distance_stop_pct": 0.5,
        "distance_target_pct": 1.0,
        "score_entry": 71.2,
        "score_current": 75.1,
        "market_entry": "NEUTRO",
        "market_current": "ALCISTA",
        "result": "EN SEGUIMIENTO"
      }
    ]
  },
  "orders": {
    "updated": "14-07-2026 01:19 PM Colombia",
    "mode": "PAPER_ONLY",
    "count": 595,
    "detail_file": "paper/paper_orders.json",
    "orders": []
  },
  "trades": {
    "updated": "14-07-2026 01:19 PM Colombia",
    "mode": "PAPER_ONLY",
    "count": 295,
    "detail_file": "paper/paper_trades.json",
    "trades": []
  },
  "risk": {
    "updated": "14-07-2026 01:19 PM Colombia",
    "version": "V4.5",
    "mode": "PAPER_TRADING_SIMULATED",
    "market_state": {
      "estado": "ALCISTA",
      "score": 8,
      "spy20": 1.73,
      "qqq20": 0.16,
      "drivers": {
        "ARKK": {
          "ticker": "ARKK",
          "estado": "POSITIVO",
          "score": 3,
          "mom20": 5.32,
          "mom5": -1.87
        },
        "BTC-USD": {
          "ticker": "BTC-USD",
          "estado": "POSITIVO",
          "score": 3,
          "mom20": 5.71,
          "mom5": 2.04
        },
        "CL=F": {
          "ticker": "CL=F",
          "estado": "NEUTRO",
          "score": 0,
          "mom20": -6.86,
          "mom5": 12.24
        },
        "ETH-USD": {
          "ticker": "ETH-USD",
          "estado": "POSITIVO",
          "score": 3,
          "mom20": 15.41,
          "mom5": 7.17
        },
        "QQQ": {
          "ticker": "QQQ",
          "estado": "POSITIVO",
          "score": 3,
          "mom20": 0.16,
          "mom5": 1.73
        },
        "SOXX": {
          "ticker": "SOXX",
          "estado": "NEUTRO",
          "score": 0,
          "mom20": -3.92,
          "mom5": 3.8
        },
        "SPY": {
          "ticker": "SPY",
          "estado": "FUERTE",
          "score": 6,
          "mom20": 1.73,
          "mom5": 0.66
        },
        "XLE": {
          "ticker": "XLE",
          "estado": "NEUTRO",
          "score": 0,
          "mom20": -0.76,
          "mom5": 3.78
        }
      },
      "sectores": {
        "chips": {
          "estado": "NEUTRO +",
          "score": 3,
          "mom20_prom": -1.88,
          "detalle": "SOXX -3.92% · QQQ 0.16%",
          "drivers": [
            "SOXX",
            "QQQ"
          ]
        },
        "energia": {
          "estado": "NEUTRO",
          "score": 0,
          "mom20_prom": -3.81,
          "detalle": "XLE -0.76% · CL=F -6.86%",
          "drivers": [
            "XLE",
            "CL=F"
          ]
        },
        "cripto": {
          "estado": "NEUTRO +",
          "score": 3,
          "mom20_prom": 10.56,
          "detalle": "BTC-USD 5.71% · ETH-USD 15.41%",
          "drivers": [
            "BTC-USD",
            "ETH-USD"
          ]
        },
        "tech_ia": {
          "estado": "ACOMPAÑA",
          "score": 7,
          "mom20_prom": 2.4,
          "detalle": "QQQ 0.16% · ARKK 5.32% · SPY 1.73%",
          "drivers": [
            "QQQ",
            "ARKK",
            "SPY"
          ]
        }
      }
    },
    "risk_config": {
      "capital_inicial": 5000.0,
      "riesgo_por_operacion_pct": 1.0,
      "max_posicion_pct": 20.0,
      "max_operaciones_abiertas": 20,
      "max_exposicion_total_pct": 80.0,
      "comision_por_operacion_pct": 0.05,
      "slippage_pct": 0.05,
      "spread_pct": 0.03,
      "pausar_si_perdidas_seguidas": 8,
      "bloquear_si_perdidas_seguidas": 12,
      "rr_minimo": 1.5,
      "volumen_relativo_minimo": 0.2,
      "permitir_buy_strong_en_mercado_debil": false,
      "max_riesgo_total_abierto_pct": 10.0,
      "modo_defensivo_drawdown_pct": 30.0,
      "bloquear_entradas_drawdown_pct": 35.0,
      "activar_reglas_operativas": true,
      "usar_exposicion_como_bloqueo": true,
      "usar_riesgo_abierto_como_bloqueo": true,
      "usar_drawdown_como_bloqueo": true,
      "permitir_buy_strong_en_modo_defensivo_drawdown": true,
      "permitir_buy_strong_sobre_exposicion": false,
      "permitir_buy_strong_sobre_riesgo": false,
      "max_dias_holding": 2.0
    },
    "summary_from_bot": {
      "max_drawdown_pct": 27.55,
      "max_drawdown_usd": 1974.74,
      "racha_max_perdidas": 14,
      "racha_max_ganadas": 6,
      "racha_actual_tipo": "PERDIDAS",
      "racha_actual": 5,
      "exposicion_abierta_usd": 3741.18,
      "exposicion_abierta_pct": 67.23,
      "riesgo_total_abierto_usd": 67.92,
      "riesgo_total_abierto_pct": 1.22,
      "operaciones_abiertas": 5,
      "max_operaciones_abiertas": 20
    },
    "metrics_from_bot": {
      "profit_factor": 1.1,
      "ganancia_promedio_pct": 6.91,
      "perdida_promedio_pct": -2.85,
      "ratio_ganancia_perdida": 2.42,
      "expectativa_pct_por_operacion": 0.36,
      "total_ganado_usd": 6035.24,
      "total_perdido_usd": 5470.64,
      "sharpe_ratio": 0.478,
      "sortino_ratio": 1.166,
      "calmar_ratio": null,
      "cagr_estimado_pct": null,
      "periodo_dias": 55,
      "win_rate_pct": 32.88,
      "avg_win_usd": 62.22,
      "avg_loss_usd": 27.63,
      "expectancy_usd": 1.91,
      "payoff_ratio": 2.25,
      "avg_holding_dias": 4.1,
      "winrate_por_sector": [
        {
          "sector": "Tecnología",
          "trades": 48,
          "win_rate_pct": 39.6,
          "pnl_usd": 701.11
        },
        {
          "sector": "Equipos chips",
          "trades": 8,
          "win_rate_pct": 62.5,
          "pnl_usd": 330.52
        },
        {
          "sector": "Salud",
          "trades": 27,
          "win_rate_pct": 33.3,
          "pnl_usd": 219.37
        },
        {
          "sector": "Finanzas",
          "trades": 17,
          "win_rate_pct": 47.1,
          "pnl_usd": 183.2
        },
        {
          "sector": "Datos / Software",
          "trades": 3,
          "win_rate_pct": 66.7,
          "pnl_usd": 154.43
        },
        {
          "sector": "ETF Chips",
          "trades": 3,
          "win_rate_pct": 66.7,
          "pnl_usd": 152.08
        },
        {
          "sector": "Ciberseguridad",
          "trades": 5,
          "win_rate_pct": 60.0,
          "pnl_usd": 133.8
        },
        {
          "sector": "ETF Biotech",
          "trades": 2,
          "win_rate_pct": 100.0,
          "pnl_usd": 118.62
        },
        {
          "sector": "Entretenimiento",
          "trades": 2,
          "win_rate_pct": 50.0,
          "pnl_usd": 102.03
        },
        {
          "sector": "Movilidad aérea",
          "trades": 5,
          "win_rate_pct": 60.0,
          "pnl_usd": 91.94
        },
        {
          "sector": "IA",
          "trades": 6,
          "win_rate_pct": 50.0,
          "pnl_usd": 82.36
        },
        {
          "sector": "ETF Tecnología",
          "trades": 5,
          "win_rate_pct": 40.0,
          "pnl_usd": 67.3
        },
        {
          "sector": "Trading",
          "trades": 5,
          "win_rate_pct": 40.0,
          "pnl_usd": 43.67
        },
        {
          "sector": "Seguros",
          "trades": 2,
          "win_rate_pct": 50.0,
          "pnl_usd": 39.16
        },
        {
          "sector": "Redes / IA",
          "trades": 3,
          "win_rate_pct": 66.7,
          "pnl_usd": 39.06
        },
        {
          "sector": "ETF Dow",
          "trades": 4,
          "win_rate_pct": 75.0,
          "pnl_usd": 36.46
        },
        {
          "sector": "ETF Industrial",
          "trades": 2,
          "win_rate_pct": 50.0,
          "pnl_usd": 27.46
        },
        {
          "sector": "ETF Salud",
          "trades": 5,
          "win_rate_pct": 40.0,
          "pnl_usd": 22.51
        },
        {
          "sector": "ETF Russell",
          "trades": 4,
          "win_rate_pct": 50.0,
          "pnl_usd": 15.92
        },
        {
          "sector": "ETF Finanzas",
          "trades": 3,
          "win_rate_pct": 33.3,
          "pnl_usd": 13.26
        },
        {
          "sector": "ETF Nasdaq",
          "trades": 4,
          "win_rate_pct": 50.0,
          "pnl_usd": 10.55
        },
        {
          "sector": "Fintech",
          "trades": 3,
          "win_rate_pct": 33.3,
          "pnl_usd": 0.48
        },
        {
          "sector": "Materiales",
          "trades": 2,
          "win_rate_pct": 0.0,
          "pnl_usd": -15.89
        },
        {
          "sector": "ETF Real Estate",
          "trades": 2,
          "win_rate_pct": 0.0,
          "pnl_usd": -18.25
        },
        {
          "sector": "ETF Dividendos",
          "trades": 2,
          "win_rate_pct": 0.0,
          "pnl_usd": -22.91
        },
        {
          "sector": "Aerolíneas",
          "trades": 4,
          "win_rate_pct": 50.0,
          "pnl_usd": -23.63
        },
        {
          "sector": "IA / Chips",
          "trades": 8,
          "win_rate_pct": 12.5,
          "pnl_usd": -27.44
        },
        {
          "sector": "Industrial",
          "trades": 9,
          "win_rate_pct": 33.3,
          "pnl_usd": -30.67
        },
        {
          "sector": "Pagos",
          "trades": 4,
          "win_rate_pct": 25.0,
          "pnl_usd": -44.95
        },
        {
          "sector": "Autos eléctricos",
          "trades": 4,
          "win_rate_pct": 25.0,
          "pnl_usd": -47.55
        },
        {
          "sector": "Software",
          "trades": 2,
          "win_rate_pct": 0.0,
          "pnl_usd": -51.94
        },
        {
          "sector": "ETF Materiales",
          "trades": 2,
          "win_rate_pct": 0.0,
          "pnl_usd": -53.56
        },
        {
          "sector": "ETF Robótica",
          "trades": 2,
          "win_rate_pct": 0.0,
          "pnl_usd": -55.47
        },
        {
          "sector": "IA / Software",
          "trades": 4,
          "win_rate_pct": 25.0,
          "pnl_usd": -56.02
        },
        {
          "sector": "Defensa",
          "trades": 2,
          "win_rate_pct": 0.0,
          "pnl_usd": -56.54
        },
        {
          "sector": "Consumo",
          "trades": 6,
          "win_rate_pct": 16.7,
          "pnl_usd": -62.16
        },
        {
          "sector": "Autos / Tech",
          "trades": 3,
          "win_rate_pct": 0.0,
          "pnl_usd": -62.61
        },
        {
          "sector": "ETF Innovación",
          "trades": 4,
          "win_rate_pct": 25.0,
          "pnl_usd": -80.94
        },
        {
          "sector": "ETF Mercado",
          "trades": 5,
          "win_rate_pct": 0.0,
          "pnl_usd": -81.09
        },
        {
          "sector": "Fintech IA",
          "trades": 3,
          "win_rate_pct": 0.0,
          "pnl_usd": -83.6
        },
        {
          "sector": "Autos",
          "trades": 4,
          "win_rate_pct": 25.0,
          "pnl_usd": -101.03
        },
        {
          "sector": "Chips",
          "trades": 23,
          "win_rate_pct": 30.4,
          "pnl_usd": -102.69
        },
        {
          "sector": "Automatización",
          "trades": 5,
          "win_rate_pct": 0.0,
          "pnl_usd": -116.29
        },
        {
          "sector": "Cruceros",
          "trades": 3,
          "win_rate_pct": 0.0,
          "pnl_usd": -122.95
        },
        {
          "sector": "Fotónica / IA",
          "trades": 2,
          "win_rate_pct": 0.0,
          "pnl_usd": -126.33
        },
        {
          "sector": "Energía",
          "trades": 9,
          "win_rate_pct": 0.0,
          "pnl_usd": -233.09
        }
      ]
    },
    "diagnostic_from_bot": {
      "modo": "ACTIVO",
      "riesgo_sistema": "ALTO",
      "mercado": "ALCISTA",
      "mensaje": "Sistema en simulación con control de riesgo; validar varios meses antes de dinero real.",
      "alertas": []
    },
    "warnings": [
      "Diagnóstico general marca riesgo ALTO."
    ],
    "can_open_more_positions": true,
    "remaining_position_slots": 15,
    "exposure_pct": 75.3,
    "open_risk_pct": 1.36,
    "operational_rules": {
      "version": "V4.4",
      "estado": "NORMAL",
      "exposicion_abierta_pct": 67.23,
      "riesgo_abierto_pct": 1.22,
      "drawdown_pct": 27.55,
      "max_exposicion_total_pct": 80.0,
      "max_riesgo_total_abierto_pct": 10.0,
      "modo_defensivo_drawdown_pct": 30.0,
      "bloquear_entradas_drawdown_pct": 35.0,
      "bloqueos_generados": 105,
      "motivo_principal": "Exposición resultante superaría límite: 85.2%",
      "reglas_activas": {
        "exposicion": true,
        "riesgo_abierto": true,
        "drawdown": true
      },
      "nota": "V4.4 usa métricas existentes como reglas operativas de entrada. No duplica el motor de riesgo."
    }
  },
  "audit": {
    "updated": "14-07-2026 01:19 PM Colombia",
    "version": "V4.5",
    "mode": "AUDITORIA_BLOQUEOS_EXISTENTES",
    "summary": {
      "blocked_count": 50,
      "buy_candidates_count": 110,
      "open_positions_count": 5,
      "warnings_count": 1,
      "main_block_reason": "Exposición resultante superaría límite: 85.2%"
    },
    "warnings": [
      "Diagnóstico general marca riesgo ALTO."
    ],
    "block_reasons": [
      {
        "reason": "Exposición resultante superaría límite: 85.2%",
        "count": 49
      },
      {
        "reason": "Confirmación baja",
        "count": 1
      }
    ],
    "blocked_signals": [
      {
        "id": "BLOCK-1",
        "date": "2026-07-14",
        "ticker": "GS",
        "signal": "BUY STRONG",
        "reason": "Exposición resultante superaría límite: 85.2%",
        "risk": "MEDIO",
        "rr": 1.7,
        "score": 94.3,
        "price": 1130.16,
        "exposure_pct": 67.23,
        "open_risk_pct": 1.22,
        "drawdown_pct": 27.55,
        "operational_rule": true,
        "decision": "BLOCKED_BY_OPERATIONAL_RULE"
      },
      {
        "id": "BLOCK-2",
        "date": "2026-07-14",
        "ticker": "AAPL",
        "signal": "BUY",
        "reason": "Exposición resultante superaría límite: 85.2%",
        "risk": "BAJO",
        "rr": 1.7,
        "score": 85.4,
        "price": 315.08,
        "exposure_pct": 67.23,
        "open_risk_pct": 1.22,
        "drawdown_pct": 27.55,
        "operational_rule": true,
        "decision": "BLOCKED_BY_OPERATIONAL_RULE"
      },
      {
        "id": "BLOCK-3",
        "date": "2026-07-14",
        "ticker": "ESTC",
        "signal": "BUY",
        "reason": "Exposición resultante superaría límite: 85.2%",
        "risk": "BAJO",
        "rr": 1.7,
        "score": 85.4,
        "price": 62.24,
        "exposure_pct": 67.23,
        "open_risk_pct": 1.22,
        "drawdown_pct": 27.55,
        "operational_rule": true,
        "decision": "BLOCKED_BY_OPERATIONAL_RULE"
      },
      {
        "id": "BLOCK-4",
        "date": "2026-07-14",
        "ticker": "VGT",
        "signal": "BUY",
        "reason": "Exposición resultante superaría límite: 85.2%",
        "risk": "BAJO",
        "rr": 1.7,
        "score": 85.2,
        "price": 117.49,
        "exposure_pct": 67.23,
        "open_risk_pct": 1.22,
        "drawdown_pct": 27.55,
        "operational_rule": true,
        "decision": "BLOCKED_BY_OPERATIONAL_RULE"
      },
      {
        "id": "BLOCK-5",
        "date": "2026-07-14",
        "ticker": "ZM",
        "signal": "BUY",
        "reason": "Exposición resultante superaría límite: 85.2%",
        "risk": "BAJO",
        "rr": 1.7,
        "score": 83.0,
        "price": 90.69,
        "exposure_pct": 67.23,
        "open_risk_pct": 1.22,
        "drawdown_pct": 27.55,
        "operational_rule": true,
        "decision": "BLOCKED_BY_OPERATIONAL_RULE"
      },
      {
        "id": "BLOCK-6",
        "date": "2026-07-14",
        "ticker": "ARKK",
        "signal": "BUY",
        "reason": "Exposición resultante superaría límite: 85.2%",
        "risk": "BAJO",
        "rr": 1.7,
        "score": 82.3,
        "price": 79.67,
        "exposure_pct": 67.23,
        "open_risk_pct": 1.22,
        "drawdown_pct": 27.55,
        "operational_rule": true,
        "decision": "BLOCKED_BY_OPERATIONAL_RULE"
      },
      {
        "id": "BLOCK-7",
        "date": "2026-07-14",
        "ticker": "SOUN",
        "signal": "BUY",
        "reason": "Exposición resultante superaría límite: 85.2%",
        "risk": "BAJO",
        "rr": 1.68,
        "score": 80.4,
        "price": 6.76,
        "exposure_pct": 67.23,
        "open_risk_pct": 1.22,
        "drawdown_pct": 27.55,
        "operational_rule": true,
        "decision": "BLOCKED_BY_OPERATIONAL_RULE"
      },
      {
        "id": "BLOCK-8",
        "date": "2026-07-14",
        "ticker": "XLK",
        "signal": "BUY",
        "reason": "Exposición resultante superaría límite: 85.2%",
        "risk": "BAJO",
        "rr": 1.7,
        "score": 79.7,
        "price": 184.38,
        "exposure_pct": 67.23,
        "open_risk_pct": 1.22,
        "drawdown_pct": 27.55,
        "operational_rule": true,
        "decision": "BLOCKED_BY_OPERATIONAL_RULE"
      },
      {
        "id": "BLOCK-9",
        "date": "2026-07-14",
        "ticker": "NOW",
        "signal": "BUY",
        "reason": "Exposición resultante superaría límite: 85.2%",
        "risk": "BAJO",
        "rr": 1.7,
        "score": 76.0,
        "price": 106.08,
        "exposure_pct": 67.23,
        "open_risk_pct": 1.22,
        "drawdown_pct": 27.55,
        "operational_rule": true,
        "decision": "BLOCKED_BY_OPERATIONAL_RULE"
      },
      {
        "id": "BLOCK-10",
        "date": "2026-07-14",
        "ticker": "GOOGL",
        "signal": "BUY",
        "reason": "Exposición resultante superaría límite: 85.2%",
        "risk": "BAJO",
        "rr": 1.7,
        "score": 75.8,
        "price": 357.77,
        "exposure_pct": 67.23,
        "open_risk_pct": 1.22,
        "drawdown_pct": 27.55,
        "operational_rule": true,
        "decision": "BLOCKED_BY_OPERATIONAL_RULE"
      },
      {
        "id": "BLOCK-11",
        "date": "2026-07-14",
        "ticker": "TXN",
        "signal": "BUY",
        "reason": "Exposición resultante superaría límite: 85.2%",
        "risk": "BAJO",
        "rr": 1.7,
        "score": 79.8,
        "price": 306.94,
        "exposure_pct": 67.23,
        "open_risk_pct": 1.22,
        "drawdown_pct": 27.55,
        "operational_rule": true,
        "decision": "BLOCKED_BY_OPERATIONAL_RULE"
      },
      {
        "id": "BLOCK-12",
        "date": "2026-07-14",
        "ticker": "COIN",
        "signal": "BUY",
        "reason": "Exposición resultante superaría límite: 85.2%",
        "risk": "BAJO",
        "rr": 1.7,
        "score": 72.6,
        "price": 161.83,
        "exposure_pct": 67.23,
        "open_risk_pct": 1.22,
        "drawdown_pct": 27.55,
        "operational_rule": true,
        "decision": "BLOCKED_BY_OPERATIONAL_RULE"
      },
      {
        "id": "BLOCK-13",
        "date": "2026-07-14",
        "ticker": "ASML",
        "signal": "BUY",
        "reason": "Confirmación baja",
        "risk": "BAJO",
        "rr": 1.7,
        "score": 66.2,
        "price": 1795.16,
        "exposure_pct": 67.23,
        "open_risk_pct": 1.22,
        "drawdown_pct": 27.55,
        "operational_rule": false,
        "decision": "BLOCKED_BY_EXISTING_RULE"
      },
      {
        "id": "BLOCK-14",
        "date": "2026-07-14",
        "ticker": "SOFI",
        "signal": "BUY",
        "reason": "Exposición resultante superaría límite: 85.2%",
        "risk": "BAJO",
        "rr": 1.69,
        "score": 86.7,
        "price": 18.61,
        "exposure_pct": 67.23,
        "open_risk_pct": 1.22,
        "drawdown_pct": 27.55,
        "operational_rule": true,
        "decision": "BLOCKED_BY_OPERATIONAL_RULE"
      },
      {
        "id": "BLOCK-15",
        "date": "2026-07-14",
        "ticker": "MS",
        "signal": "BUY",
        "reason": "Exposición resultante superaría límite: 85.2%",
        "risk": "BAJO",
        "rr": 1.7,
        "score": 83.7,
        "price": 227.25,
        "exposure_pct": 67.23,
        "open_risk_pct": 1.22,
        "drawdown_pct": 27.55,
        "operational_rule": true,
        "decision": "BLOCKED_BY_OPERATIONAL_RULE"
      },
      {
        "id": "BLOCK-16",
        "date": "2026-07-14",
        "ticker": "AXP",
        "signal": "BUY",
        "reason": "Exposición resultante superaría límite: 85.2%",
        "risk": "BAJO",
        "rr": 1.7,
        "score": 82.5,
        "price": 355.47,
        "exposure_pct": 67.23,
        "open_risk_pct": 1.22,
        "drawdown_pct": 27.55,
        "operational_rule": true,
        "decision": "BLOCKED_BY_OPERATIONAL_RULE"
      },
      {
        "id": "BLOCK-17",
        "date": "2026-07-14",
        "ticker": "ETN",
        "signal": "BUY",
        "reason": "Exposición resultante superaría límite: 85.2%",
        "risk": "BAJO",
        "rr": 1.7,
        "score": 82.3,
        "price": 412.39,
        "exposure_pct": 67.23,
        "open_risk_pct": 1.22,
        "drawdown_pct": 27.55,
        "operational_rule": true,
        "decision": "BLOCKED_BY_OPERATIONAL_RULE"
      },
      {
        "id": "BLOCK-18",
        "date": "2026-07-14",
        "ticker": "SYM",
        "signal": "BUY",
        "reason": "Exposición resultante superaría límite: 85.2%",
        "risk": "BAJO",
        "rr": 1.69,
        "score": 81.3,
        "price": 43.47,
        "exposure_pct": 67.23,
        "open_risk_pct": 1.22,
        "drawdown_pct": 27.55,
        "operational_rule": true,
        "decision": "BLOCKED_BY_OPERATIONAL_RULE"
      },
      {
        "id": "BLOCK-19",
        "date": "2026-07-14",
        "ticker": "NEE",
        "signal": "BUY",
        "reason": "Exposición resultante superaría límite: 85.2%",
        "risk": "BAJO",
        "rr": 1.69,
        "score": 79.4,
        "price": 89.49,
        "exposure_pct": 67.23,
        "open_risk_pct": 1.22,
        "drawdown_pct": 27.55,
        "operational_rule": true,
        "decision": "BLOCKED_BY_OPERATIONAL_RULE"
      },
      {
        "id": "BLOCK-20",
        "date": "2026-07-14",
        "ticker": "EOG",
        "signal": "BUY",
        "reason": "Exposición resultante superaría límite: 85.2%",
        "risk": "BAJO",
        "rr": 1.7,
        "score": 78.1,
        "price": 137.59,
        "exposure_pct": 67.23,
        "open_risk_pct": 1.22,
        "drawdown_pct": 27.55,
        "operational_rule": true,
        "decision": "BLOCKED_BY_OPERATIONAL_RULE"
      },
      {
        "id": "BLOCK-21",
        "date": "2026-07-14",
        "ticker": "KKR",
        "signal": "BUY",
        "reason": "Exposición resultante superaría límite: 85.2%",
        "risk": "BAJO",
        "rr": 1.7,
        "score": 76.2,
        "price": 97.75,
        "exposure_pct": 67.23,
        "open_risk_pct": 1.22,
        "drawdown_pct": 27.55,
        "operational_rule": true,
        "decision": "BLOCKED_BY_OPERATIONAL_RULE"
      },
      {
        "id": "BLOCK-22",
        "date": "2026-07-14",
        "ticker": "BAC",
        "signal": "BUY",
        "reason": "Exposición resultante superaría límite: 85.2%",
        "risk": "BAJO",
        "rr": 1.69,
        "score": 83.3,
        "price": 60.14,
        "exposure_pct": 67.23,
        "open_risk_pct": 1.22,
        "drawdown_pct": 27.55,
        "operational_rule": true,
        "decision": "BLOCKED_BY_OPERATIONAL_RULE"
      },
      {
        "id": "BLOCK-23",
        "date": "2026-07-14",
        "ticker": "JPM",
        "signal": "BUY",
        "reason": "Exposición resultante superaría límite: 85.2%",
        "risk": "BAJO",
        "rr": 1.7,
        "score": 82.0,
        "price": 339.15,
        "exposure_pct": 67.23,
        "open_risk_pct": 1.22,
        "drawdown_pct": 27.55,
        "operational_rule": true,
        "decision": "BLOCKED_BY_OPERATIONAL_RULE"
      },
      {
        "id": "BLOCK-24",
        "date": "2026-07-14",
        "ticker": "ABNB",
        "signal": "BUY",
        "reason": "Exposición resultante superaría límite: 85.2%",
        "risk": "BAJO",
        "rr": 1.7,
        "score": 81.2,
        "price": 146.41,
        "exposure_pct": 67.23,
        "open_risk_pct": 1.22,
        "drawdown_pct": 27.55,
        "operational_rule": true,
        "decision": "BLOCKED_BY_OPERATIONAL_RULE"
      },
      {
        "id": "BLOCK-25",
        "date": "2026-07-14",
        "ticker": "EXPE",
        "signal": "BUY",
        "reason": "Exposición resultante superaría límite: 85.2%",
        "risk": "BAJO",
        "rr": 1.7,
        "score": 81.0,
        "price": 268.6,
        "exposure_pct": 67.23,
        "open_risk_pct": 1.22,
        "drawdown_pct": 27.55,
        "operational_rule": true,
        "decision": "BLOCKED_BY_OPERATIONAL_RULE"
      },
      {
        "id": "BLOCK-26",
        "date": "2026-07-14",
        "ticker": "NVO",
        "signal": "BUY",
        "reason": "Exposición resultante superaría límite: 85.2%",
        "risk": "BAJO",
        "rr": 1.71,
        "score": 80.9,
        "price": 49.22,
        "exposure_pct": 67.23,
        "open_risk_pct": 1.22,
        "drawdown_pct": 27.55,
        "operational_rule": true,
        "decision": "BLOCKED_BY_OPERATIONAL_RULE"
      },
      {
        "id": "BLOCK-27",
        "date": "2026-07-14",
        "ticker": "PH",
        "signal": "BUY",
        "reason": "Exposición resultante superaría límite: 85.2%",
        "risk": "BAJO",
        "rr": 1.7,
        "score": 79.9,
        "price": 960.92,
        "exposure_pct": 67.23,
        "open_risk_pct": 1.22,
        "drawdown_pct": 27.55,
        "operational_rule": true,
        "decision": "BLOCKED_BY_OPERATIONAL_RULE"
      },
      {
        "id": "BLOCK-28",
        "date": "2026-07-14",
        "ticker": "IBKR",
        "signal": "BUY",
        "reason": "Exposición resultante superaría límite: 85.2%",
        "risk": "BAJO",
        "rr": 1.7,
        "score": 79.9,
        "price": 95.41,
        "exposure_pct": 67.23,
        "open_risk_pct": 1.22,
        "drawdown_pct": 27.55,
        "operational_rule": true,
        "decision": "BLOCKED_BY_OPERATIONAL_RULE"
      },
      {
        "id": "BLOCK-29",
        "date": "2026-07-14",
        "ticker": "FANG",
        "signal": "BUY",
        "reason": "Exposición resultante superaría límite: 85.2%",
        "risk": "BAJO",
        "rr": 1.7,
        "score": 79.8,
        "price": 189.91,
        "exposure_pct": 67.23,
        "open_risk_pct": 1.22,
        "drawdown_pct": 27.55,
        "operational_rule": true,
        "decision": "BLOCKED_BY_OPERATIONAL_RULE"
      },
      {
        "id": "BLOCK-30",
        "date": "2026-07-14",
        "ticker": "WMB",
        "signal": "BUY",
        "reason": "Exposición resultante superaría límite: 85.2%",
        "risk": "BAJO",
        "rr": 1.7,
        "score": 79.7,
        "price": 75.81,
        "exposure_pct": 67.23,
        "open_risk_pct": 1.22,
        "drawdown_pct": 27.55,
        "operational_rule": true,
        "decision": "BLOCKED_BY_OPERATIONAL_RULE"
      },
      {
        "id": "BLOCK-31",
        "date": "2026-07-14",
        "ticker": "XLE",
        "signal": "BUY",
        "reason": "Exposición resultante superaría límite: 85.2%",
        "risk": "BAJO",
        "rr": 1.69,
        "score": 79.7,
        "price": 56.73,
        "exposure_pct": 67.23,
        "open_risk_pct": 1.22,
        "drawdown_pct": 27.55,
        "operational_rule": true,
        "decision": "BLOCKED_BY_OPERATIONAL_RULE"
      },
      {
        "id": "BLOCK-32",
        "date": "2026-07-14",
        "ticker": "UNH",
        "signal": "BUY",
        "reason": "Exposición resultante superaría límite: 85.2%",
        "risk": "BAJO",
        "rr": 1.7,
        "score": 79.3,
        "price": 424.87,
        "exposure_pct": 67.23,
        "open_risk_pct": 1.22,
        "drawdown_pct": 27.55,
        "operational_rule": true,
        "decision": "BLOCKED_BY_OPERATIONAL_RULE"
      },
      {
        "id": "BLOCK-33",
        "date": "2026-07-14",
        "ticker": "XLU",
        "signal": "BUY",
        "reason": "Exposición resultante superaría límite: 85.2%",
        "risk": "BAJO",
        "rr": 1.68,
        "score": 79.3,
        "price": 45.63,
        "exposure_pct": 67.23,
        "open_risk_pct": 1.22,
        "drawdown_pct": 27.55,
        "operational_rule": true,
        "decision": "BLOCKED_BY_OPERATIONAL_RULE"
      },
      {
        "id": "BLOCK-34",
        "date": "2026-07-14",
        "ticker": "AFL",
        "signal": "BUY",
        "reason": "Exposición resultante superaría límite: 85.2%",
        "risk": "BAJO",
        "rr": 1.71,
        "score": 79.0,
        "price": 122.57,
        "exposure_pct": 67.23,
        "open_risk_pct": 1.22,
        "drawdown_pct": 27.55,
        "operational_rule": true,
        "decision": "BLOCKED_BY_OPERATIONAL_RULE"
      },
      {
        "id": "BLOCK-35",
        "date": "2026-07-14",
        "ticker": "DIA",
        "signal": "BUY",
        "reason": "Exposición resultante superaría límite: 85.2%",
        "risk": "BAJO",
        "rr": 1.7,
        "score": 78.2,
        "price": 524.2,
        "exposure_pct": 67.23,
        "open_risk_pct": 1.22,
        "drawdown_pct": 27.55,
        "operational_rule": true,
        "decision": "BLOCKED_BY_OPERATIONAL_RULE"
      },
      {
        "id": "BLOCK-36",
        "date": "2026-07-14",
        "ticker": "OXY",
        "signal": "BUY",
        "reason": "Exposición resultante superaría límite: 85.2%",
        "risk": "BAJO",
        "rr": 1.7,
        "score": 78.0,
        "price": 54.15,
        "exposure_pct": 67.23,
        "open_risk_pct": 1.22,
        "drawdown_pct": 27.55,
        "operational_rule": true,
        "decision": "BLOCKED_BY_OPERATIONAL_RULE"
      },
      {
        "id": "BLOCK-37",
        "date": "2026-07-14",
        "ticker": "OKE",
        "signal": "BUY",
        "reason": "Exposición resultante superaría límite: 85.2%",
        "risk": "BAJO",
        "rr": 1.7,
        "score": 77.8,
        "price": 91.46,
        "exposure_pct": 67.23,
        "open_risk_pct": 1.22,
        "drawdown_pct": 27.55,
        "operational_rule": true,
        "decision": "BLOCKED_BY_OPERATIONAL_RULE"
      },
      {
        "id": "BLOCK-38",
        "date": "2026-07-14",
        "ticker": "XOM",
        "signal": "BUY",
        "reason": "Exposición resultante superaría límite: 85.2%",
        "risk": "BAJO",
        "rr": 1.7,
        "score": 77.8,
        "price": 144.82,
        "exposure_pct": 67.23,
        "open_risk_pct": 1.22,
        "drawdown_pct": 27.55,
        "operational_rule": true,
        "decision": "BLOCKED_BY_OPERATIONAL_RULE"
      },
      {
        "id": "BLOCK-39",
        "date": "2026-07-14",
        "ticker": "TGT",
        "signal": "BUY",
        "reason": "Exposición resultante superaría límite: 85.2%",
        "risk": "BAJO",
        "rr": 1.7,
        "score": 77.6,
        "price": 133.68,
        "exposure_pct": 67.23,
        "open_risk_pct": 1.22,
        "drawdown_pct": 27.55,
        "operational_rule": true,
        "decision": "BLOCKED_BY_OPERATIONAL_RULE"
      },
      {
        "id": "BLOCK-40",
        "date": "2026-07-14",
        "ticker": "PGR",
        "signal": "BUY",
        "reason": "Exposición resultante superaría límite: 85.2%",
        "risk": "BAJO",
        "rr": 1.7,
        "score": 77.2,
        "price": 227.18,
        "exposure_pct": 67.23,
        "open_risk_pct": 1.22,
        "drawdown_pct": 27.55,
        "operational_rule": true,
        "decision": "BLOCKED_BY_OPERATIONAL_RULE"
      },
      {
        "id": "BLOCK-41",
        "date": "2026-07-14",
        "ticker": "KMI",
        "signal": "BUY",
        "reason": "Exposición resultante superaría límite: 85.2%",
        "risk": "BAJO",
        "rr": 1.67,
        "score": 76.9,
        "price": 32.45,
        "exposure_pct": 67.23,
        "open_risk_pct": 1.22,
        "drawdown_pct": 27.55,
        "operational_rule": true,
        "decision": "BLOCKED_BY_OPERATIONAL_RULE"
      },
      {
        "id": "BLOCK-42",
        "date": "2026-07-14",
        "ticker": "KO",
        "signal": "BUY",
        "reason": "Exposición resultante superaría límite: 85.2%",
        "risk": "BAJO",
        "rr": 1.69,
        "score": 76.6,
        "price": 83.31,
        "exposure_pct": 67.23,
        "open_risk_pct": 1.22,
        "drawdown_pct": 27.55,
        "operational_rule": true,
        "decision": "BLOCKED_BY_OPERATIONAL_RULE"
      },
      {
        "id": "BLOCK-43",
        "date": "2026-07-14",
        "ticker": "CVX",
        "signal": "BUY",
        "reason": "Exposición resultante superaría límite: 85.2%",
        "risk": "BAJO",
        "rr": 1.7,
        "score": 76.5,
        "price": 181.49,
        "exposure_pct": 67.23,
        "open_risk_pct": 1.22,
        "drawdown_pct": 27.55,
        "operational_rule": true,
        "decision": "BLOCKED_BY_OPERATIONAL_RULE"
      },
      {
        "id": "BLOCK-44",
        "date": "2026-07-14",
        "ticker": "QQQ",
        "signal": "BUY",
        "reason": "Exposición resultante superaría límite: 85.2%",
        "risk": "BAJO",
        "rr": 1.7,
        "score": 76.3,
        "price": 721.58,
        "exposure_pct": 67.23,
        "open_risk_pct": 1.22,
        "drawdown_pct": 27.55,
        "operational_rule": true,
        "decision": "BLOCKED_BY_OPERATIONAL_RULE"
      },
      {
        "id": "BLOCK-45",
        "date": "2026-07-14",
        "ticker": "ABBV",
        "signal": "BUY",
        "reason": "Exposición resultante superaría límite: 85.2%",
        "risk": "BAJO",
        "rr": 1.7,
        "score": 74.9,
        "price": 245.44,
        "exposure_pct": 67.23,
        "open_risk_pct": 1.22,
        "drawdown_pct": 27.55,
        "operational_rule": true,
        "decision": "BLOCKED_BY_OPERATIONAL_RULE"
      },
      {
        "id": "BLOCK-46",
        "date": "2026-07-14",
        "ticker": "WFC",
        "signal": "BUY",
        "reason": "Exposición resultante superaría límite: 85.2%",
        "risk": "BAJO",
        "rr": 1.7,
        "score": 74.9,
        "price": 85.02,
        "exposure_pct": 67.23,
        "open_risk_pct": 1.22,
        "drawdown_pct": 27.55,
        "operational_rule": true,
        "decision": "BLOCKED_BY_OPERATIONAL_RULE"
      },
      {
        "id": "BLOCK-47",
        "date": "2026-07-14",
        "ticker": "COP",
        "signal": "BUY",
        "reason": "Exposición resultante superaría límite: 85.2%",
        "risk": "BAJO",
        "rr": 1.7,
        "score": 74.4,
        "price": 110.93,
        "exposure_pct": 67.23,
        "open_risk_pct": 1.22,
        "drawdown_pct": 27.55,
        "operational_rule": true,
        "decision": "BLOCKED_BY_OPERATIONAL_RULE"
      },
      {
        "id": "BLOCK-48",
        "date": "2026-07-14",
        "ticker": "GILD",
        "signal": "BUY",
        "reason": "Exposición resultante superaría límite: 85.2%",
        "risk": "BAJO",
        "rr": 1.7,
        "score": 74.3,
        "price": 130.77,
        "exposure_pct": 67.23,
        "open_risk_pct": 1.22,
        "drawdown_pct": 27.55,
        "operational_rule": true,
        "decision": "BLOCKED_BY_OPERATIONAL_RULE"
      },
      {
        "id": "BLOCK-49",
        "date": "2026-07-14",
        "ticker": "XLV",
        "signal": "BUY",
        "reason": "Exposición resultante superaría límite: 85.2%",
        "risk": "BAJO",
        "rr": 1.71,
        "score": 74.2,
        "price": 158.5,
        "exposure_pct": 67.23,
        "open_risk_pct": 1.22,
        "drawdown_pct": 27.55,
        "operational_rule": true,
        "decision": "BLOCKED_BY_OPERATIONAL_RULE"
      },
      {
        "id": "BLOCK-50",
        "date": "2026-07-14",
        "ticker": "JNJ",
        "signal": "BUY",
        "reason": "Exposición resultante superaría límite: 85.2%",
        "risk": "BAJO",
        "rr": 1.7,
        "score": 74.0,
        "price": 252.93,
        "exposure_pct": 67.23,
        "open_risk_pct": 1.22,
        "drawdown_pct": 27.55,
        "operational_rule": true,
        "decision": "BLOCKED_BY_OPERATIONAL_RULE"
      }
    ],
    "buy_candidates": [
      {
        "ticker": "GS",
        "signal": "BUY STRONG",
        "score": 94.3,
        "risk": "MEDIO",
        "already_open": false,
        "entry": "1118.38 - 1135.21",
        "stop": 1113.33,
        "target": 1158.77
      },
      {
        "ticker": "AAPL",
        "signal": "BUY",
        "score": 85.4,
        "risk": "BAJO",
        "already_open": false,
        "entry": "311.93 - 316.42",
        "stop": 310.59,
        "target": 322.7
      },
      {
        "ticker": "ESTC",
        "signal": "BUY",
        "score": 85.4,
        "risk": "BAJO",
        "already_open": false,
        "entry": "61.17 - 62.71",
        "stop": 60.71,
        "target": 64.86
      },
      {
        "ticker": "VGT",
        "signal": "BUY",
        "score": 85.2,
        "risk": "BAJO",
        "already_open": false,
        "entry": "116.38 - 117.97",
        "stop": 115.9,
        "target": 120.19
      },
      {
        "ticker": "ZM",
        "signal": "BUY",
        "score": 83.0,
        "risk": "BAJO",
        "already_open": false,
        "entry": "89.58 - 91.17",
        "stop": 89.1,
        "target": 93.4
      },
      {
        "ticker": "ARKK",
        "signal": "BUY",
        "score": 82.3,
        "risk": "BAJO",
        "already_open": false,
        "entry": "78.77 - 80.06",
        "stop": 78.38,
        "target": 81.86
      },
      {
        "ticker": "SOUN",
        "signal": "BUY",
        "score": 80.4,
        "risk": "BAJO",
        "already_open": false,
        "entry": "6.62 - 6.83",
        "stop": 6.56,
        "target": 7.11
      },
      {
        "ticker": "XLK",
        "signal": "BUY",
        "score": 79.7,
        "risk": "BAJO",
        "already_open": false,
        "entry": "182.45 - 185.21",
        "stop": 181.62,
        "target": 189.08
      },
      {
        "ticker": "NOW",
        "signal": "BUY",
        "score": 76.0,
        "risk": "BAJO",
        "already_open": false,
        "entry": "104.02 - 106.96",
        "stop": 103.13,
        "target": 111.09
      },
      {
        "ticker": "GOOGL",
        "signal": "BUY",
        "score": 75.8,
        "risk": "BAJO",
        "already_open": false,
        "entry": "354.28 - 359.26",
        "stop": 352.79,
        "target": 366.24
      },
      {
        "ticker": "UBER",
        "signal": "BUY",
        "score": 70.0,
        "risk": "BAJO",
        "already_open": true,
        "entry": "70.94 - 72.4",
        "stop": 70.5,
        "target": 74.44
      },
      {
        "ticker": "TXN",
        "signal": "BUY",
        "score": 79.8,
        "risk": "BAJO",
        "already_open": false,
        "entry": "301.68 - 309.19",
        "stop": 299.43,
        "target": 319.71
      },
      {
        "ticker": "COIN",
        "signal": "BUY",
        "score": 72.6,
        "risk": "BAJO",
        "already_open": false,
        "entry": "158.44 - 163.28",
        "stop": 156.99,
        "target": 170.06
      },
      {
        "ticker": "ASML",
        "signal": "BUY",
        "score": 66.2,
        "risk": "BAJO",
        "already_open": false,
        "entry": "1763.61 - 1808.69",
        "stop": 1750.09,
        "target": 1871.79
      },
      {
        "ticker": "SOFI",
        "signal": "BUY",
        "score": 86.7,
        "risk": "BAJO",
        "already_open": false,
        "entry": "18.29 - 18.76",
        "stop": 18.14,
        "target": 19.42
      },
      {
        "ticker": "MS",
        "signal": "BUY",
        "score": 83.7,
        "risk": "BAJO",
        "already_open": false,
        "entry": "225.07 - 228.18",
        "stop": 224.14,
        "target": 232.54
      },
      {
        "ticker": "AXP",
        "signal": "BUY",
        "score": 82.5,
        "risk": "BAJO",
        "already_open": false,
        "entry": "352.31 - 356.83",
        "stop": 350.96,
        "target": 363.15
      },
      {
        "ticker": "ETN",
        "signal": "BUY",
        "score": 82.3,
        "risk": "BAJO",
        "already_open": false,
        "entry": "406.47 - 414.93",
        "stop": 403.94,
        "target": 426.76
      },
      {
        "ticker": "SYM",
        "signal": "BUY",
        "score": 81.3,
        "risk": "BAJO",
        "already_open": false,
        "entry": "42.7 - 43.8",
        "stop": 42.36,
        "target": 45.34
      },
      {
        "ticker": "BX",
        "signal": "BUY",
        "score": 80.0,
        "risk": "BAJO",
        "already_open": true,
        "entry": "123.69 - 125.69",
        "stop": 123.09,
        "target": 128.48
      },
      {
        "ticker": "NEE",
        "signal": "BUY",
        "score": 79.4,
        "risk": "BAJO",
        "already_open": false,
        "entry": "88.97 - 89.71",
        "stop": 88.75,
        "target": 90.74
      },
      {
        "ticker": "EOG",
        "signal": "BUY",
        "score": 78.1,
        "risk": "BAJO",
        "already_open": false,
        "entry": "136.33 - 138.13",
        "stop": 135.79,
        "target": 140.65
      },
      {
        "ticker": "KKR",
        "signal": "BUY",
        "score": 76.2,
        "risk": "BAJO",
        "already_open": false,
        "entry": "96.58 - 98.25",
        "stop": 96.07,
        "target": 100.6
      },
      {
        "ticker": "BAC",
        "signal": "BUY",
        "score": 83.3,
        "risk": "BAJO",
        "already_open": false,
        "entry": "59.71 - 60.33",
        "stop": 59.52,
        "target": 61.19
      },
      {
        "ticker": "JPM",
        "signal": "BUY",
        "score": 82.0,
        "risk": "BAJO",
        "already_open": false,
        "entry": "336.51 - 340.28",
        "stop": 335.37,
        "target": 345.57
      },
      {
        "ticker": "ABNB",
        "signal": "BUY",
        "score": 81.2,
        "risk": "BAJO",
        "already_open": false,
        "entry": "144.71 - 147.14",
        "stop": 143.98,
        "target": 150.54
      },
      {
        "ticker": "EXPE",
        "signal": "BUY",
        "score": 81.0,
        "risk": "BAJO",
        "already_open": false,
        "entry": "264.41 - 270.4",
        "stop": 262.62,
        "target": 278.77
      },
      {
        "ticker": "NVO",
        "signal": "BUY",
        "score": 80.9,
        "risk": "BAJO",
        "already_open": false,
        "entry": "48.81 - 49.39",
        "stop": 48.64,
        "target": 50.2
      },
      {
        "ticker": "PH",
        "signal": "BUY",
        "score": 79.9,
        "risk": "BAJO",
        "already_open": false,
        "entry": "952.86 - 964.38",
        "stop": 949.4,
        "target": 980.51
      },
      {
        "ticker": "IBKR",
        "signal": "BUY",
        "score": 79.9,
        "risk": "BAJO",
        "already_open": false,
        "entry": "94.03 - 96.0",
        "stop": 93.43,
        "target": 98.77
      },
      {
        "ticker": "FANG",
        "signal": "BUY",
        "score": 79.8,
        "risk": "BAJO",
        "already_open": false,
        "entry": "188.03 - 190.71",
        "stop": 187.22,
        "target": 194.47
      },
      {
        "ticker": "WMB",
        "signal": "BUY",
        "score": 79.7,
        "risk": "BAJO",
        "already_open": false,
        "entry": "75.1 - 76.11",
        "stop": 74.8,
        "target": 77.53
      },
      {
        "ticker": "XLE",
        "signal": "BUY",
        "score": 79.7,
        "risk": "BAJO",
        "already_open": false,
        "entry": "56.35 - 56.89",
        "stop": 56.19,
        "target": 57.64
      },
      {
        "ticker": "UNH",
        "signal": "BUY",
        "score": 79.3,
        "risk": "BAJO",
        "already_open": false,
        "entry": "421.16 - 426.46",
        "stop": 419.57,
        "target": 433.87
      },
      {
        "ticker": "XLU",
        "signal": "BUY",
        "score": 79.3,
        "risk": "BAJO",
        "already_open": false,
        "entry": "45.41 - 45.73",
        "stop": 45.31,
        "target": 46.18
      },
      {
        "ticker": "AFL",
        "signal": "BUY",
        "score": 79.0,
        "risk": "BAJO",
        "already_open": false,
        "entry": "121.79 - 122.9",
        "stop": 121.46,
        "target": 124.45
      },
      {
        "ticker": "DIA",
        "signal": "BUY",
        "score": 78.2,
        "risk": "BAJO",
        "already_open": false,
        "entry": "522.29 - 525.02",
        "stop": 521.47,
        "target": 528.83
      },
      {
        "ticker": "OXY",
        "signal": "BUY",
        "score": 78.0,
        "risk": "BAJO",
        "already_open": false,
        "entry": "53.58 - 54.39",
        "stop": 53.34,
        "target": 55.53
      },
      {
        "ticker": "OKE",
        "signal": "BUY",
        "score": 77.8,
        "risk": "BAJO",
        "already_open": false,
        "entry": "90.65 - 91.81",
        "stop": 90.31,
        "target": 93.42
      },
      {
        "ticker": "XOM",
        "signal": "BUY",
        "score": 77.8,
        "risk": "BAJO",
        "already_open": false,
        "entry": "143.75 - 145.28",
        "stop": 143.29,
        "target": 147.42
      },
      {
        "ticker": "TGT",
        "signal": "BUY",
        "score": 77.6,
        "risk": "BAJO",
        "already_open": false,
        "entry": "132.24 - 134.3",
        "stop": 131.62,
        "target": 137.18
      },
      {
        "ticker": "XBI",
        "signal": "BUY",
        "score": 77.2,
        "risk": "BAJO",
        "already_open": true,
        "entry": "154.53 - 156.65",
        "stop": 153.89,
        "target": 159.61
      },
      {
        "ticker": "PGR",
        "signal": "BUY",
        "score": 77.2,
        "risk": "BAJO",
        "already_open": false,
        "entry": "225.07 - 228.08",
        "stop": 224.16,
        "target": 232.31
      },
      {
        "ticker": "KMI",
        "signal": "BUY",
        "score": 76.9,
        "risk": "BAJO",
        "already_open": false,
        "entry": "32.22 - 32.55",
        "stop": 32.12,
        "target": 33.0
      },
      {
        "ticker": "KO",
        "signal": "BUY",
        "score": 76.6,
        "risk": "BAJO",
        "already_open": false,
        "entry": "82.7 - 83.56",
        "stop": 82.44,
        "target": 84.77
      },
      {
        "ticker": "CVX",
        "signal": "BUY",
        "score": 76.5,
        "risk": "BAJO",
        "already_open": false,
        "entry": "180.17 - 182.06",
        "stop": 179.6,
        "target": 184.7
      },
      {
        "ticker": "QQQ",
        "signal": "BUY",
        "score": 76.3,
        "risk": "BAJO",
        "already_open": false,
        "entry": "716.33 - 723.82",
        "stop": 714.09,
        "target": 734.31
      },
      {
        "ticker": "ABBV",
        "signal": "BUY",
        "score": 74.9,
        "risk": "BAJO",
        "already_open": false,
        "entry": "243.06 - 246.46",
        "stop": 242.04,
        "target": 251.22
      },
      {
        "ticker": "WFC",
        "signal": "BUY",
        "score": 74.9,
        "risk": "BAJO",
        "already_open": false,
        "entry": "84.31 - 85.32",
        "stop": 84.01,
        "target": 86.74
      },
      {
        "ticker": "COP",
        "signal": "BUY",
        "score": 74.4,
        "risk": "BAJO",
        "already_open": false,
        "entry": "109.99 - 111.33",
        "stop": 109.59,
        "target": 113.21
      },
      {
        "ticker": "GILD",
        "signal": "BUY",
        "score": 74.3,
        "risk": "BAJO",
        "already_open": false,
        "entry": "129.39 - 131.36",
        "stop": 128.8,
        "target": 134.11
      },
      {
        "ticker": "XLV",
        "signal": "BUY",
        "score": 74.2,
        "risk": "BAJO",
        "already_open": false,
        "entry": "157.48 - 158.94",
        "stop": 157.04,
        "target": 160.99
      },
      {
        "ticker": "JNJ",
        "signal": "BUY",
        "score": 74.0,
        "risk": "BAJO",
        "already_open": false,
        "entry": "250.67 - 253.89",
        "stop": 249.71,
        "target": 258.4
      },
      {
        "ticker": "DVN",
        "signal": "BUY",
        "score": 73.0,
        "risk": "BAJO",
        "already_open": false,
        "entry": "42.61 - 43.27",
        "stop": 42.41,
        "target": 44.2
      },
      {
        "ticker": "RIG",
        "signal": "BUY",
        "score": 72.9,
        "risk": "BAJO",
        "already_open": false,
        "entry": "5.19 - 5.3",
        "stop": 5.15,
        "target": 5.45
      },
      {
        "ticker": "HAL",
        "signal": "BUY",
        "score": 71.9,
        "risk": "BAJO",
        "already_open": false,
        "entry": "34.84 - 35.34",
        "stop": 34.68,
        "target": 36.05
      },
      {
        "ticker": "ROK",
        "signal": "BUY",
        "score": 67.3,
        "risk": "BAJO",
        "already_open": false,
        "entry": "464.88 - 472.32",
        "stop": 462.64,
        "target": 482.75
      },
      {
        "ticker": "SCHD",
        "signal": "BUY",
        "score": 78.2,
        "risk": "BAJO",
        "already_open": false,
        "entry": "32.13 - 32.31",
        "stop": 32.08,
        "target": 32.55
      },
      {
        "ticker": "HOOD",
        "signal": "BUY",
        "score": 75.3,
        "risk": "BAJO",
        "already_open": false,
        "entry": "110.6 - 113.93",
        "stop": 109.61,
        "target": 118.58
      },
      {
        "ticker": "HYG",
        "signal": "BUY",
        "score": 74.3,
        "risk": "BAJO",
        "already_open": false,
        "entry": "79.58 - 79.67",
        "stop": 79.55,
        "target": 79.8
      },
      {
        "ticker": "BLK",
        "signal": "BUY",
        "score": 72.5,
        "risk": "BAJO",
        "already_open": false,
        "entry": "1020.13 - 1033.0",
        "stop": 1016.27,
        "target": 1051.01
      },
      {
        "ticker": "SPOT",
        "signal": "BUY",
        "score": 70.5,
        "risk": "BAJO",
        "already_open": false,
        "entry": "475.8 - 484.3",
        "stop": 473.25,
        "target": 496.2
      },
      {
        "ticker": "LULU",
        "signal": "BUY",
        "score": 70.4,
        "risk": "BAJO",
        "already_open": false,
        "entry": "116.34 - 118.54",
        "stop": 115.68,
        "target": 121.61
      },
      {
        "ticker": "IWM",
        "signal": "BUY",
        "score": 70.2,
        "risk": "BAJO",
        "already_open": false,
        "entry": "293.2 - 295.41",
        "stop": 292.54,
        "target": 298.51
      },
      {
        "ticker": "XLRE",
        "signal": "BUY",
        "score": 70.1,
        "risk": "BAJO",
        "already_open": false,
        "entry": "44.27 - 44.58",
        "stop": 44.17,
        "target": 45.01
      },
      {
        "ticker": "FIS",
        "signal": "BUY",
        "score": 69.9,
        "risk": "BAJO",
        "already_open": false,
        "entry": "40.21 - 40.91",
        "stop": 40.01,
        "target": 41.88
      },
      {
        "ticker": "TM",
        "signal": "BUY",
        "score": 69.3,
        "risk": "BAJO",
        "already_open": false,
        "entry": "175.19 - 176.84",
        "stop": 174.7,
        "target": 179.15
      },
      {
        "ticker": "BKR",
        "signal": "BUY",
        "score": 67.8,
        "risk": "BAJO",
        "already_open": false,
        "entry": "56.76 - 57.66",
        "stop": 56.49,
        "target": 58.91
      },
      {
        "ticker": "LLY",
        "signal": "BUY",
        "score": 67.4,
        "risk": "BAJO",
        "already_open": false,
        "entry": "1143.01 - 1163.75",
        "stop": 1136.78,
        "target": 1192.8
      },
      {
        "ticker": "MRK",
        "signal": "BUY",
        "score": 67.1,
        "risk": "BAJO",
        "already_open": false,
        "entry": "119.7 - 121.46",
        "stop": 119.17,
        "target": 123.94
      },
      {
        "ticker": "XPEV",
        "signal": "BUY",
        "score": 66.3,
        "risk": "BAJO",
        "already_open": false,
        "entry": "13.21 - 13.47",
        "stop": 13.13,
        "target": 13.84
      },
      {
        "ticker": "CME",
        "signal": "BUY",
        "score": 64.7,
        "risk": "BAJO",
        "already_open": false,
        "entry": "241.56 - 245.24",
        "stop": 240.46,
        "target": 250.39
      },
      {
        "ticker": "DELL",
        "signal": "BUY",
        "score": 88.3,
        "risk": "MEDIO",
        "already_open": false,
        "entry": "447.73 - 462.87",
        "stop": 443.19,
        "target": 484.06
      },
      {
        "ticker": "ANET",
        "signal": "BUY",
        "score": 87.2,
        "risk": "MEDIO",
        "already_open": false,
        "entry": "179.0 - 184.23",
        "stop": 177.43,
        "target": 191.55
      },
      {
        "ticker": "PANW",
        "signal": "BUY",
        "score": 84.1,
        "risk": "MEDIO",
        "already_open": false,
        "entry": "345.23 - 354.47",
        "stop": 342.46,
        "target": 367.41
      },
      {
        "ticker": "FTNT",
        "signal": "BUY",
        "score": 84.0,
        "risk": "MEDIO",
        "already_open": false,
        "entry": "163.48 - 166.97",
        "stop": 162.43,
        "target": 171.87
      },
      {
        "ticker": "ZS",
        "signal": "BUY",
        "score": 83.4,
        "risk": "MEDIO",
        "already_open": false,
        "entry": "149.93 - 153.94",
        "stop": 148.73,
        "target": 159.54
      },
      {
        "ticker": "META",
        "signal": "BUY",
        "score": 83.2,
        "risk": "MEDIO",
        "already_open": false,
        "entry": "652.39 - 666.22",
        "stop": 648.25,
        "target": 685.57
      },
      {
        "ticker": "HPQ",
        "signal": "BUY",
        "score": 81.8,
        "risk": "MEDIO",
        "already_open": false,
        "entry": "24.47 - 24.88",
        "stop": 24.35,
        "target": 25.46
      },
      {
        "ticker": "CHKP",
        "signal": "BUY",
        "score": 81.0,
        "risk": "MEDIO",
        "already_open": false,
        "entry": "134.89 - 137.55",
        "stop": 134.09,
        "target": 141.27
      }
    ],
    "notes": [
      "Este archivo no crea lógica nueva; resume bloqueos ya existentes en historial_senales.json.",
      "Sirve para explicar por qué el bot no abrió compras aunque hubiera señales BUY."
    ]
  },
  "operational_rules": {
    "version": "V4.4",
    "estado": "NORMAL",
    "exposicion_abierta_pct": 67.23,
    "riesgo_abierto_pct": 1.22,
    "drawdown_pct": 27.55,
    "max_exposicion_total_pct": 80.0,
    "max_riesgo_total_abierto_pct": 10.0,
    "modo_defensivo_drawdown_pct": 30.0,
    "bloquear_entradas_drawdown_pct": 35.0,
    "bloqueos_generados": 105,
    "motivo_principal": "Exposición resultante superaría límite: 85.2%",
    "reglas_activas": {
      "exposicion": true,
      "riesgo_abierto": true,
      "drawdown": true
    },
    "nota": "V4.4 usa métricas existentes como reglas operativas de entrada. No duplica el motor de riesgo."
  }
}